internutopia/__init__.py
internutopia/download_assets.py
internutopia/login_openxlab.py
internutopia/macros.py
internutopia/set_assets_path.py
internutopia/setup_conda_pypi.py
internutopia/core/__init__.py
internutopia/core/gym_env.py
internutopia/core/runner.py
internutopia/core/vec_env.py
internutopia/core/config/__init__.py
internutopia/core/config/distribution/__init__.py
internutopia/core/config/metric/__init__.py
internutopia/core/config/object/__init__.py
internutopia/core/config/robot/__init__.py
internutopia/core/config/sensor/__init__.py
internutopia/core/config/task/__init__.py
internutopia/core/config/task/reward.py
internutopia/core/datahub/__init__.py
internutopia/core/datahub/datahub.py
internutopia/core/datahub/isaac_data.py
internutopia/core/datahub/model_data.py
internutopia/core/distribution/__init__.py
internutopia/core/distribution/launcher.py
internutopia/core/distribution/runner_proxy.py
internutopia/core/object/__init__.py
internutopia/core/object/object.py
internutopia/core/register/__init__.py
internutopia/core/register/register.py
internutopia/core/robot/__init__.py
internutopia/core/robot/articulation.py
internutopia/core/robot/articulation_action.py
internutopia/core/robot/articulation_subset.py
internutopia/core/robot/controller.py
internutopia/core/robot/rigid_body.py
internutopia/core/robot/robot.py
internutopia/core/robot/isaacsim/__init__.py
internutopia/core/robot/isaacsim/articulation.py
internutopia/core/robot/isaacsim/rigid_body.py
internutopia/core/scene/__init__.py
internutopia/core/scene/scene.py
internutopia/core/scene/isaacsim/__init__.py
internutopia/core/scene/isaacsim/scene.py
internutopia/core/sensor/__init__.py
internutopia/core/sensor/camera.py
internutopia/core/sensor/sensor.py
internutopia/core/sensor/isaacsim/__init__.py
internutopia/core/sensor/isaacsim/camera.py
internutopia/core/task/__init__.py
internutopia/core/task/metric.py
internutopia/core/task/reward.py
internutopia/core/task/task.py
internutopia-2.2.1.dist-info/licenses/LICENSE
internutopia-2.2.1.dist-info/METADATA
internutopia-2.2.1.dist-info/WHEEL
internutopia-2.2.1.dist-info/top_level.txt
internutopia-2.2.1.dist-info/RECORD
