Metadata-Version: 2.4
Name: internutopia
Version: 2.2.1
Summary: Easy to use omniverse isaac sim standalone package
Author: APX103
Author-email: lijialun@pjlab.org.cn
Classifier: Programming Language :: Python :: 3
Classifier: Operating System :: OS Independent
Requires-Python: >=3.10
License-File: LICENSE
Requires-Dist: addict==2.4.0
Requires-Dist: aiohttp_cors==0.7.0
Requires-Dist: httpcore==1.0.8
Requires-Dist: httpx==0.25.2
Requires-Dist: inputs==0.5
Requires-Dist: ipython==8.20.0
Requires-Dist: lcm==1.5.0
Requires-Dist: onnxruntime==1.19.2
Requires-Dist: openai==1.29.0
Requires-Dist: pyyaml==6.0.1
Requires-Dist: rsl-rl-lib==2.2.1
Requires-Dist: transformers==4.26.1
Requires-Dist: vuer==0.0.32rc7
Dynamic: author
Dynamic: author-email
Dynamic: classifier
Dynamic: description
Dynamic: description-content-type
Dynamic: license-file
Dynamic: requires-dist
Dynamic: requires-python
Dynamic: summary
